impira/__init__.py
impira/api_v2.py
impira/config.py
impira/fmt.py
impira/schema.py
impira/types.py
impira/utils.py
impira/version.py
impira/cmd/__init__.py
impira/cmd/__main__.py
impira/cmd/bootstrap.py
impira/cmd/capture.py
impira/cmd/snapshot.py
impira/cmd/snapshot_collections.py
impira/cmd/utils.py
impira/tools/__init__.py
impira/tools/impira.py
impira/tools/textract.py
impira/tools/tool.py
impira-0.1.14.dist-info/LICENSE
impira-0.1.14.dist-info/METADATA
impira-0.1.14.dist-info/WHEEL
impira-0.1.14.dist-info/entry_points.txt
impira-0.1.14.dist-info/top_level.txt
impira-0.1.14.dist-info/RECORD
