Metadata-Version: 2.1
Name: impira
Version: 0.1.14
Summary: Official Impira Python SDK
Home-page: https://github.com/impira/impira-python
Author: Impira Engineering
Author-email: engineering@impira.com
Project-URL: Bug Tracker, https://github.com/impira/impira-python/issues
Classifier: Programming Language :: Python :: 3
Classifier: License :: OSI Approved :: MIT License
Classifier: Operating System :: OS Independent
Requires-Python: >=3.7.4
License-File: LICENSE
Requires-Dist: python-dateutil
Requires-Dist: pydantic
Requires-Dist: requests
Provides-Extra: all
Requires-Dist: boto3 ; extra == 'all'
Requires-Dist: commonmark (>=0.9) ; extra == 'all'
Requires-Dist: enum-tools[sphinx] (>=0.9) ; extra == 'all'
Requires-Dist: myst-parser (>=0.15) ; extra == 'all'
Requires-Dist: sphinx (>=4.5) ; extra == 'all'
Requires-Dist: textract-trp ; extra == 'all'
Provides-Extra: cli
Requires-Dist: boto3 ; extra == 'cli'
Requires-Dist: textract-trp ; extra == 'cli'
Provides-Extra: doc
Requires-Dist: myst-parser (>=0.15) ; extra == 'doc'
Requires-Dist: sphinx (>=4.5) ; extra == 'doc'
Requires-Dist: commonmark (>=0.9) ; extra == 'doc'
Requires-Dist: enum-tools[sphinx] (>=0.9) ; extra == 'doc'
